lab/__init__.py
lab/cli.py
lab/configs.py
lab/experiment.py
lab/logger.py
lab/loop.py
lab/monit.py
lab/tracker.py
lab/helpers/__init__.py
lab/helpers/training_loop.py
lab/helpers/pytorch/__init__.py
lab/helpers/pytorch/device.py
lab/helpers/pytorch/module.py
lab/helpers/pytorch/seed.py
lab/helpers/pytorch/train_valid.py
lab/helpers/pytorch/datasets/__init__.py
lab/helpers/pytorch/datasets/cifar10.py
lab/helpers/pytorch/datasets/mnist.py
lab/internal/__init__.py
lab/internal/lab.py
lab/internal/analytics/__init__.py
lab/internal/analytics/analytics.py
lab/internal/analytics/sqlite.py
lab/internal/analytics/tensorboard.py
lab/internal/analytics/altair/__init__.py
lab/internal/analytics/altair/tb.py
lab/internal/analytics/matplotlib/__init__.py
lab/internal/analytics/matplotlib/sqlite.py
lab/internal/analytics/matplotlib/tb.py
lab/internal/analytics/tests/__init__.py
lab/internal/analytics/tests/indexed_matplotlib.py
lab/internal/analytics/tests/tb_altair.py
lab/internal/analytics/tests/tb_matplotlib.py
lab/internal/configs/__init__.py
lab/internal/configs/calculator.py
lab/internal/configs/config_function.py
lab/internal/configs/config_item.py
lab/internal/configs/parser.py
lab/internal/configs/sample.py
lab/internal/experiment/__init__.py
lab/internal/experiment/experiment_run.py
lab/internal/experiment/pytorch.py
lab/internal/experiment/sklearn.py
lab/internal/logger/__init__.py
lab/internal/logger/inspect.py
lab/internal/logger/iterator.py
lab/internal/logger/loop.py
lab/internal/logger/sections.py
lab/internal/logger/destinations/__init__.py
lab/internal/logger/destinations/console.py
lab/internal/logger/destinations/factory.py
lab/internal/logger/destinations/ipynb.py
lab/internal/logger/store/__init__.py
lab/internal/logger/store/artifacts.py
lab/internal/logger/store/indicators.py
lab/internal/logger/store/namespace.py
lab/internal/logger/util/__init__.py
lab/internal/logger/util/pytorch.py
lab/internal/logger/writers/__init__.py
machine_learning_lab-0.4.6.dist-info/METADATA
machine_learning_lab-0.4.6.dist-info/WHEEL
machine_learning_lab-0.4.6.dist-info/entry_points.txt
machine_learning_lab-0.4.6.dist-info/top_level.txt
machine_learning_lab-0.4.6.dist-info/RECORD
